[
    {
        "개요": "한국전력은 최근 강력한 거래량을 동반하여 장기 이동평균선을 돌파한 후, 단기 조정 과정에서 20일 이동평균선의 지지를 확인하고 반등을 시도하는 모습입니다. 8분기 연속 흑자 달성, 증권사 목표가 상향, 원전 수출 기대감 등 긍정적 뉴스가 풍부하여 단기 트레이딩 관점에서 매우 매력적인 구간으로 판단됩니다.",
        "종목정보": "한국전력(015760)",
        "기술적분석": "📈 <b>돌파 구간:</b> 2025년 6월 말, 20일 평균 거래량의 4배가 넘는 대량 거래를 동반하며 240일선(당시 약 24,000원 추정)을 강력하게 상향 돌파.<br>📉 <b>지지 구간:</b> 42,450원 고점 형성 후 조정, 최근 20일 이동평균선(약 38,500원) 부근에서 지지를 확인하며 하락을 방어.<br>🕯️ <b>캔들 패턴:</b> 2025년 8월 12일, 지지선 부근에서 아래꼬리가 긴 양봉(반등 시그널) 형성 후, 8월 13일 추가 상승하며 반등 흐름을 이어가는 긍정적 캔들 패턴.<br>📊 <b>거래량 분석:</b> 장기 이평선 돌파 시 대량의 매수 거래량이 유입되었으며, 최근 조정 구간에서는 거래량이 감소하여 건전한 조정을 보임. 반등 시 거래량 증가 여부 확인 필요.<br>🎯 <b>목표 및 손절가:</b><br>   - <b>1차 목표가:</b> 42,000원 (직전 고점)<br>   - <b>2차 목표가:</b> 45,000원 (신고가 영역, 심리적 저항선)<br>   - <b>손절가:</b> 37,500원 (직전 저점 및 20일선 이탈 시 리스크 관리)",
        "이슈": {
            "뉴스": "📰 최근 5거래일 내 실적, 증권사 리포트, 해외 사업 관련 긍정적 뉴스가 집중적으로 발생하여 주가 상승 모멘텀을 강화하고 있습니다.",
            "긍정적": "✅ <b>실적 서프라이즈:</b> 8분기 연속 영업흑자 달성 및 2분기 호실적 발표.<br>✅ <b>목표가 상향:</b> 다수 증권사에서 전기요금 인상 및 미국 원전 시장 진출 기대를 근거로 목표주가 상향 조정.<br>✅ <b>원전 수출 기대감:</b> 베트남과의 정상회담을 계기로 원전 수주에 대한 기대감 부각.",
            "부정적": "⚠️ <b>누적 적자 부담:</b> 흑자 전환에도 불구하고 여전히 40조원에 달하는 누적 적자는 장기적인 재무 부담 요인.<br>⚠️ <b>일부 투자자 매도세:</b> 최근 주가 상승에 따른 개인 투자자 중심의 차익 실현 매물 출회.",
            "요약": "💡 기술적으로 단기 지지선에서 반등하는 초기 국면이며, 강력한 뉴스 모멘텀이 뒷받침되고 있어 <b>단기적 진입 타이밍으로 매우 적절</b>하다고 판단됩니다. 조정 시 매수 관점이 유효해 보입니다."
        },
        "최종의견": "<b>매수 (Buy)</b> ⭐️⭐️⭐️⭐️<br><b>근거:</b> 기술적으로 주요 지지선에서의 반등이 확인되었고, 실적 개선과 원전 수출이라는 강력한 뉴스 모멘텀이 결합되어 추가 상승 가능성이 매우 높습니다. 단, 장기 이평선이 아닌 20일선 지지이므로, 손절 라인을 철저히 지키는 단기 트레이딩 전략이 유효합니다."
    },
    {
        "개요": "GH신소재는 코로나19 재확산 테마와 함께 장기 이동평균선(240일, 480일)을 대량 거래로 돌파 후, 해당 이평선에서 정확한 지지 테스트를 거치고 반등하는 기술적 분석의 정석적인 패턴을 보이고 있습니다. 단기 테마성 이슈가 부각되고 있어 변동성이 클 수 있으나, 기술적 분석 조건에 완벽하게 부합하여 단기 트레이딩 대상으로 주목할 만합니다.",
        "종목정보": "GH신소재(130500)",
        "기술적분석": "📈 <b>돌파 구간:</b> 2025년 8월 8일, 20일 평균 거래량의 50배가 넘는 폭발적인 거래량을 동반하며 240일선(2,848원)과 480일선(2,856원)을 동시에 상향 돌파.<br>📉 <b>지지 구간:</b> 8월 12일, 장중 장기 이평선(240일/480일)을 하회했으나 종가상 지켜내며 완벽한 지지 테스트 완료.<br>🕯️ <b>캔들 패턴:</b> 8월 13일, 지지선 위에서 시가가 형성된 후 양봉으로 마감하며 기술적 반등의 신뢰도를 높이는 캔들 패턴 형성.<br>📊 <b>거래량 분석:</b> 돌파 시 거래량이 폭발적으로 증가하였고, 이후 지지 테스트 과정에서는 거래량이 급감하여 매물 소화가 잘 이루어진 것으로 판단. 재상승 시 거래량 증가가 필수적.<br>🎯 <b>목표 및 손절가:</b><br>   - <b>1차 목표가:</b> 3,200원 (돌파 시 고점 부근)<br>   - <b>2차 목표가:</b> 3,400원 (2024년 12월 매물대)<br>   - <b>손절가:</b> 2,800원 (장기 이평선 및 지지선 이탈 시 즉시 리스크 관리)",
        "이슈": {
            "뉴스": "📰 최근 제주 지역 코로나19 확산 소식이 전해지면서 시간외 거래에서 강세를 보이는 등, 관련 테마주로서의 모멘텀이 다시 부각되고 있습니다.",
            "긍정적": "✅ <b>테마성 모멘텀:</b> 국내외 호흡기 질환(코로나19, 독감 등) 유행 시 음압병실 관련주로 부각되는 경향이 있음. 최근 관련 뉴스로 투자 심리 개선.<br>✅ <b>견조한 과거 실적:</b> 과거 공시를 통해 확인된 영업이익의 큰 폭 증가는 기업의 펀더멘털이 뒷받침되고 있음을 시사.",
            "부정적": "⚠️ <b>테마 변동성:</b> 주가 상승 동력이 특정 테마에 의존적이므로, 이슈가 소멸될 경우 급격한 주가 하락의 위험이 존재함.<br>⚠️ <b>상대적 거래량 부족:</b> 평상시 거래량이 적어 급등락에 취약할 수 있음.",
            "요약": "💡 기술적 분석의 모든 조건을 완벽하게 충족하는 '교과서적인 차트'입니다. 최근 긍정적 테마가 다시 부각되고 있어 <b>단기적 진입 타이밍으로서 최적의 조건</b>을 갖추었습니다. 변동성을 고려한 분할 매수 전략이 유리합니다."
        },
        "최종의견": "<b>적극 매수 (Strong Buy)</b> ⭐️⭐️⭐️⭐️⭐️<br><b>근거:</b> 제시된 기술적 분석 조건에 100% 부합하는 완벽한 차트 패턴을 보이고 있습니다. 대량거래를 동반한 장기 이평선 돌파, 정확한 지지 테스트, 반등 캔들 확인 및 긍정적인 뉴스 모멘텀까지 단기 트레이딩의 모든 요소를 갖추고 있어 높은 성공 확률이 기대됩니다."
    }
]