[
    {
        "개요": "오로스테크놀로지는 최근 반도체 업황 개선 기대감을 바탕으로 장기 이동평균선을 대량 거래와 함께 돌파한 후, 추가 상승을 모색하는 흐름을 보이고 있습니다. 기술적 분석과 뉴스 모멘텀이 일치하여 단기 트레이딩 관점에서 긍정적인 신호가 포착되었습니다.",
        "종목정보": "오로스테크놀로지(322310)",
        "기술적분석": "📈 **돌파 구간**: 2025년 9월 11일, 480일 이동평균선(약 22,700원)을 상향 돌파했습니다.\n📉 **지지 구간**: 돌파 이후 주가가 급락하지 않고 24,000원대에서 견조한 지지 흐름을 형성하며 에너지를 응축하고 있습니다.\n📊 **캔들 패턴**: 2025년 9월 15일, 단기 조정을 마치고 반등하는 양봉 캔들을 형성하여 추가 상승 의지를 보여주고 있습니다.\n🔊 **거래량 분석**: 돌파 당일(9/11) 거래량은 39.6만 주로, 직전 20거래일 평균 거래량(약 8.7만 주) 대비 4.5배 이상 급증하여 돌파의 신뢰도를 높였습니다.\n🎯 **목표 및 손절가**:\n  - **1차 목표**: 전고점 부근인 25,300원\n  - **2차 목표**: 심리적 저항선인 27,000원\n  - **손절가**: 480일 이동평균선 하향 이탈 시 (22,500원)",
        "이슈": {
            "뉴스": "최근(9/11) 미국 오라클의 실적 호조와 필라델피아 반도체 지수 급등 소식이 전해지면서 국내 반도체 관련주 전반에 긍정적인 투자 심리가 확산되었습니다. 이는 오로스테크놀로지의 주가 급등에 직접적인 모멘텀으로 작용했습니다.",
            "긍정적": "✅ 반도체 업황 턴어라운드 기대감\n✅ 강력한 거래량을 동반한 장기 추세선 돌파\n✅ 정배열 초기 국면 진입",
            "부정적": "⚠️ 단기 급등에 따른 차익 실현 매물 출회 가능성\n⚠️ 글로벌 증시 변동성에 따른 영향",
            "요약": "기술적으로 장기 하락 추세를 마감하고 새로운 상승 추세를 시작하는 중요한 변곡점에 위치해 있으며, 강력한 업황 모멘텀이 이를 뒷받침하고 있습니다. 단기 급등 후 숨 고르기 국면으로, 현재가 부근에서 분할 매수 전략이 유효해 보입니다."
        },
        "최종의견": "🌟 **단기 매수 (Positive)**\n강력한 거래량을 동반한 장기 이평선 돌파는 신뢰도 높은 추세 전환 신호입니다. 여기에 반도체 업황 개선이라는 명확한 모멘텀이 더해져, 단기적인 가격 변동은 있을 수 있으나 상승 추세는 이어질 가능성이 높다고 판단됩니다."
    },
    {
        "개요": "폴라리스오피스는 AI 관련 신규 서비스 탑재라는 구체적인 호재를 바탕으로 장기 이동평균선을 돌파한 후, 교과서적인 지지 테스트까지 마친 상태입니다. 기술적 분석과 뉴스 분석 양쪽 모두에서 긍정적인 신호가 발생하여 단기적인 주가 상승 기대감이 높습니다.",
        "종목정보": "폴라리스오피스(041020)",
        "기술적분석": "📈 **돌파 구간**: 2025년 9월 12일, 240일 이동평균선(약 5,700원)을 대량 거래를 동반하며 상향 돌파했습니다.\n📉 **지지 구간**: 2025년 9월 15일, 장중 조정을 보이며 240일선(저가 5,690원)을 정확히 터치한 후 반등에 성공, 기술적으로 매우 의미 있는 지지 라인을 확인했습니다.\n📊 **캔들 패턴**: 9월 15일 캔들은 긴 아래꼬리를 형성하며 마감되었습니다. 이는 지지선 부근에서 강력한 매수세가 유입되었음을 의미하며, 추가 하락보다는 반등 가능성에 무게를 싣는 신호입니다.\n🔊 **거래량 분석**: 돌파 당일(9/12) 거래량은 109만 주로, 직전 20거래일 평균 거래량(약 27만 주) 대비 4배 이상 급증하며 시장의 높은 관심을 입증했습니다.\n🎯 **목표 및 손절가**:\n  - **1차 목표**: 직전 고점 및 480일선이 위치한 6,000원\n  - **2차 목표**: 주요 매물대 상단인 6,500원\n  - **손절가**: 지지선으로 확인된 240일선 하향 이탈 시 (5,650원)",
        "이슈": {
            "뉴스": "최근(9/11) 구글의 AI 기반 이미지 편집 툴 '나노바나나'를 자사 서비스에 탑재한다는 소식을 발표했습니다. 이는 폴라리스오피스의 서비스 경쟁력을 강화하고, 향후 유료 구독자 증대 및 사용자당 평균 수익(ARPPU) 개선으로 이어질 수 있는 실질적인 호재입니다.",
            "긍정적": "✅ AI 신규 서비스 탑재로 인한 성장 모멘텀 확보\n✅ 실적 개선에 대한 기대감 형성\n✅ 장기 이평선 돌파 및 지지 확인이라는 안정적인 기술적 패턴",
            "부정적": "⚠️ 480일 이동평균선(약 6,000원)의 저항 가능성\n⚠️ AI 테마의 높은 변동성 및 시장 상황에 따른 영향",
            "요약": "기술적 분석의 정석적인 '돌파 후 지지' 패턴과 기업의 본질적인 가치를 높이는 긍정적 뉴스가 결합되어, 단기 트레이딩 관점에서 신뢰도 높은 진입 타이밍으로 판단됩니다."
        },
        "최종의견": "🌟 **단기 매수 (Strong Positive)**\n장기 이평선 돌파와 지지 테스트라는 기술적 안정성에, 서비스 경쟁력 강화 및 수익성 개선이라는 펀더멘털 모멘텀까지 겸비했습니다. 명확한 지지선이 확인된 만큼, 손익비가 좋은 매매가 가능할 것으로 기대됩니다."
    }
]